twenty/__init__.py
twenty/__main__.py
twenty-0.1.0.dist-info/METADATA
twenty-0.1.0.dist-info/WHEEL
twenty-0.1.0.dist-info/entry_points.txt
twenty-0.1.0.dist-info/RECORD
