Metadata-Version: 2.3
Name: twenty
Version: 0.1.0
Summary: 20-20-20
Author-email: skarfie123 <rahulpai@rocketmail.com>
Requires-Python: >=3.8
